markr/__init__.py
markr-0.0.1.data/scripts/markr
markr-0.0.1.dist-info/LICENSE
markr-0.0.1.dist-info/METADATA
markr-0.0.1.dist-info/WHEEL
markr-0.0.1.dist-info/top_level.txt
markr-0.0.1.dist-info/RECORD
