Metadata-Version: 2.1
Name: markr
Version: 0.0.1
Summary: Package and script allowing marks to be associated with files
Home-page: https://github.com/dang3r/markr
Author: Daniel Cardoza
Author-email: dan@danielcardoaa.com
License: MIT
Platform: UNKNOWN
Requires-Python: >=3.4.0
Requires-Dist: pyxattr
